orbipatch/__init__.py
orbipatch/api.py
orbipatch-2022.3.6.1.dist-info/METADATA
orbipatch-2022.3.6.1.dist-info/WHEEL
orbipatch-2022.3.6.1.dist-info/top_level.txt
orbipatch-2022.3.6.1.dist-info/RECORD
