Metadata-Version: 2.1
Name: orbipatch
Version: 2022.3.6.1
Summary: silly project named after a niche math thing
Home-page: https://github.com/moshez/pyproject-only-example
Author-email: Moshe Zadka <orbipatch-author@devskillup.com>
License: Permission is hereby granted, free of charge, to any person obtaining a
Project-URL: Home-Page, https://github.com/moshez/pyproject-only-example
Project-URL: Issues, https://github.com/moshez/pyproject-only-example/issues
Platform: UNKNOWN
